[
  {
    "show": "O Inimigo",
    "day": "20",
    "month": "Abr",
    "hour": "16:00",
    "location": "Centro de eventos RIO+",
    "city": "Rio de Janeiro-RJ"
  },
  {
    "show": "Principados & Potestades",
    "day": "01",
    "month": "Mai",
    "hour": "19:30",
    "location": "Adonai Del Castilho",
    "city": "Rio de Janeiro-RJ"
  },
  {
    "show": "Mercador das Mascaras",
    "day": "16",
    "month": "Jun",
    "hour": "09:25",
    "location": "Posto 8 Copacabana",
    "city": "Rio de Janeiro-RJ"
  }
]